aiovkapi/__init__.py
aiovkapi-1.0.0.dist-info/METADATA
aiovkapi-1.0.0.dist-info/WHEEL
aiovkapi-1.0.0.dist-info/RECORD
