Metadata-Version: 2.1
Name: aiovkapi
Version: 1.0.0
Summary: 
License: GPLv3
Author: FeeeeK
Requires-Python: >=3.10,<4.0
Classifier: License :: Other/Proprietary License
Classifier: Programming Language :: Python :: 3
Classifier: Programming Language :: Python :: 3.10
Classifier: Programming Language :: Python :: 3.11
Requires-Dist: vkbottle (>=4.3.12,<5.0.0)
